odoo/addons/mail_template_substitute/README.rst
odoo/addons/mail_template_substitute/__init__.py
odoo/addons/mail_template_substitute/__manifest__.py
odoo/addons/mail_template_substitute/i18n/es.po
odoo/addons/mail_template_substitute/i18n/it.po
odoo/addons/mail_template_substitute/i18n/mail_template_substitute.pot
odoo/addons/mail_template_substitute/models/__init__.py
odoo/addons/mail_template_substitute/models/mail_template.py
odoo/addons/mail_template_substitute/models/mail_template_substitution_rule.py
odoo/addons/mail_template_substitute/readme/CONTRIBUTORS.md
odoo/addons/mail_template_substitute/readme/DESCRIPTION.md
odoo/addons/mail_template_substitute/readme/ROADMAP.md
odoo/addons/mail_template_substitute/readme/USAGE.md
odoo/addons/mail_template_substitute/security/mail_template_substitution_rule.xml
odoo/addons/mail_template_substitute/static/description/icon.png
odoo/addons/mail_template_substitute/static/description/index.html
odoo/addons/mail_template_substitute/tests/__init__.py
odoo/addons/mail_template_substitute/tests/test_mail_template_substitute.py
odoo/addons/mail_template_substitute/views/mail_template.xml
odoo/addons/mail_template_substitute/wizards/__init__.py
odoo/addons/mail_template_substitute/wizards/mail_compose_message.py
odoo_addon_mail_template_substitute-17.0.1.0.0.3.dist-info/METADATA
odoo_addon_mail_template_substitute-17.0.1.0.0.3.dist-info/WHEEL
odoo_addon_mail_template_substitute-17.0.1.0.0.3.dist-info/top_level.txt
odoo_addon_mail_template_substitute-17.0.1.0.0.3.dist-info/RECORD
